{
  "MONDAY": {},
  "TUESDAY": {},
  "WEDNESDAY": {
    "Superset 1 (2 rounds) ПВЗ 1-3": {
      "Вертикальная тяга": "15",
      "Болгарские выпады": "15/15"
    },
    "Superset 2 (2 rounds) ПВЗ 1-3": {
      "Отжимания в яму": "4-6",
      "Наклоны на 1 ноге": "15/15"
    },
    "Пробежка в легком темпе": {
      "бег": "20 минут"
    },
    "Пробежка интервалами": {
      "интервалы": "по 2 мин быстрее среднего и 2 минуты легко, 20-30 минут"
    }
  },
  "THURSDAY": {},
  "FRIDAY": {
    "Superset 1 (3 rounds) ПВЗ 1-3": {
      "Дим резины стоя": "15",
      "Приседания с выпрыгиванием": "15-20"
    },
    "Superset 2 (3 rounds) ПВЗ 1-3": {
      "Тяга резины к поясу": "15/15",
      "Выпады в динамике": "30"
    },
    "Superset 3 (3 rounds) ПВЗ 1-3": {
      "Треп-3": "10",
      "Скручивания 3по20": {}
    },
    "Пробежка интервалами": {
      "интервалы": "по 2 мин быстрее среднего и 2 минуты легко, 20-30 минут"
    }
  },
  "SATURDAY": {},
  "SUNDAY": {
    "Superset 1 (2 rounds) ПВЗ 1-3": {
      "Отжимания в яму": "10-15",
      "Приседания оверхед с резиной": "15"
    },
    "Superset 2 (2 rounds) ПВЗ 1-3": {
      "Подтягивания с разворотом плеч": "15",
      "Приседания оверхед с резиной": "15"
    },
    "Пробежка в легком темпе": {
      "бег": "20 минут"
    }
  }
}
